darkest_parser/__init__.py
darkest_parser/darkest.py
darkest_parser-1.1.1.dist-info/METADATA
darkest_parser-1.1.1.dist-info/WHEEL
darkest_parser-1.1.1.dist-info/RECORD
