Metadata-Version: 2.1
Name: darkest-parser
Version: 1.1.1
Summary: Parser for .darkest file
Author: syrinka
Author-email: syrinka@foxmail.com
Requires-Python: >=3.12,<4.0
Classifier: Programming Language :: Python :: 3
Requires-Dist: lark (>=1.1.8,<2.0.0)
